pentestmcp/__init__.py
pentestmcp/bloodhound.py
pentestmcp/config.py
pentestmcp/server.py
pentestmcp/config/config.json
pentestmcp/psudohash/LICENSE.md
pentestmcp/psudohash/common_padding_values.txt
pentestmcp/psudohash/psudohash.py
pentestmcp/ressources/custom_bloodhound_queries.json
pentestmcp-0.1.1.dist-info/licenses/LICENSE
pentestmcp-0.1.1.dist-info/METADATA
pentestmcp-0.1.1.dist-info/WHEEL
pentestmcp-0.1.1.dist-info/entry_points.txt
pentestmcp-0.1.1.dist-info/top_level.txt
pentestmcp-0.1.1.dist-info/RECORD
