Metadata-Version: 2.4
Name: pentestMCP
Version: 0.1.1
Summary: This is an MCP server that exposes red team tools for active directory pentesting to LLMs
Requires-Python: >=3.10
License-File: LICENSE
Requires-Dist: aiohttp>=3.12.13
Requires-Dist: mcp[cli]>=1.9.4
Requires-Dist: paramiko>=3.5.1
Requires-Dist: requests
Dynamic: license-file
